{
  "model_name": "ch32l103",
  "contexts": {
    "mcu": {
      "project_name": "ch32l103",
      "startup_file": "startup_ch32l103.S"
    },
    "clock": {
      "clock_source": "HSE",
      "pll_source": "RCC_PLLSource_HSE_Div1",
      "hse_freq_mhz": 8,
      "pll_mul": 12
    },
    "linker": {
      "flash_size": 64,
      "ram_size": 20,
      "stack_size": 2024
    },
    "usart": [
      {
        "USART1": {
          "tx_pin": "GPIO_Pin_9",
          "tx_port": "GPIOA",
          "rx_pin": "GPIO_Pin_10",
          "rx_port": "GPIOA",
          "baud_rate": 2000000,
          "word_length": 8,
          "stop_bits": 1,
          "parity": null,
          "hardware_flow_control": {
            "cts": false,
            "rts": false
          },
          "remap": null
        }
      }
    ],
    "i2c": [
      {
        "I2C1": {
          "scl_port": "GPIOB",
          "scl_pin": "GPIO_Pin_6",
          "sda_port": "GPIOB",
          "sda_pin": "GPIO_Pin_7",
          "smba_port": "GPIOB",
          "smba_pin": "GPIO_Pin_5",
          "clock_speed_khz": 100,
          "mode": "I2C_Mode_I2C",
          "duty_cycle": "I2C_DutyCycle_2",
          "own_address": "0x00",
          "ack": true,
          "acknowledged_address": 7,
          "remap": null
        }
      }
    ]
  }
}
